<?xml version="1.0" encoding="UTF-8" standalone="yes"?>
<addon id="plugin.video.mgtv"
    name="芒果TV"
    version="1.0.0"
    provider-name="yfang1644">
    <requires>
        <import addon="script.module.beautifulsoup4" version="4.3.2"/>
    </requires>
    <extension point="xbmc.python.pluginsource" library="default.py">
        <provides>video</provides>
    </extension>
    <extension point="xbmc.addon.metadata">
        <summary lang="en">Manguot Video plugin</summary>
        <summary lang="zh">QQ视频插件</summary>
        <description lang="en">Online videos from tv.sohu.com</description>
        <description lang="zh">本插件视频解析自芒果TV网站(www.mgtv.com)</description>
        <source>https://github.com/yfang1644/kodi_plugins/blob/master/plugin.video.qq</source>
		<email>yfang1644@gmail.com</email>
        <platform>all</platform>
    </extension>
</addon>
